setup.cfg
setup.py
LanguagelabApi.egg-info/PKG-INFO
LanguagelabApi.egg-info/SOURCES.txt
LanguagelabApi.egg-info/dependency_links.txt
LanguagelabApi.egg-info/entry_points.txt
LanguagelabApi.egg-info/not-zip-safe
LanguagelabApi.egg-info/requires.txt
LanguagelabApi.egg-info/top_level.txt
llapi/__init__.py
llapi/base.py
llapi/exc.py