Metadata-Version: 1.0
Name: LanguagelabApi
Version: 0.3
Summary: A Python implementation of the Languagelab API
Home-page: http://www.bitbucket.org/Splee/languagelabapi/
Author: Lee McFadden
Author-email: spleeman@gmail.com
License: MIT
Platform: UNKNOWN
Classifier: Development Status :: 4 - Beta
Classifier: Intended Audience :: Developers
Classifier: License :: OSI Approved :: MIT License
Classifier: Natural Language :: English
Classifier: Operating System :: OS Independent
Classifier: Programming Language :: Python
Classifier: Topic :: Internet :: WWW/HTTP :: Dynamic Content
Classifier: Topic :: Software Development :: Libraries :: Python Modules
